erkc63/__init__.py
erkc63/__main__.py
erkc63/account.py
erkc63/accrual.py
erkc63/bills.py
erkc63/client.py
erkc63/errors.py
erkc63/meters.py
erkc63/parsers.py
erkc63/payment.py
erkc63/utils.py
erkc63/images/paid.png
erkc63-0.2.40.dist-info/METADATA
erkc63-0.2.40.dist-info/WHEEL
erkc63-0.2.40.dist-info/licenses/LICENSE
erkc63-0.2.40.dist-info/RECORD
