Metadata-Version: 2.4
Name: erkc63
Version: 0.2.40
Summary: Клиент личного кабинета ЕРКЦ.
Project-URL: Documentation, https://github.com/dudanov/python-erkc63
Project-URL: Home Page, https://github.com/dudanov/python-erkc63
Project-URL: Issue Tracker, https://github.com/dudanov/python-erkc63/issues
Project-URL: Source Code, https://github.com/dudanov/python-erkc63.git
Author-email: Sergey Dudanov <sergey.dudanov@gmail.com>
Maintainer-email: Sergey Dudanov <sergey.dudanov@gmail.com>
License-Expression: Apache-2.0
License-File: LICENSE
Keywords: async,client,erkc63
Classifier: Development Status :: 4 - Beta
Classifier: Framework :: AsyncIO
Classifier: Intended Audience :: Developers
Classifier: Natural Language :: Russian
Classifier: Operating System :: OS Independent
Classifier: Programming Language :: Python
Classifier: Programming Language :: Python :: 3 :: Only
Classifier: Programming Language :: Python :: 3.12
Classifier: Programming Language :: Python :: 3.13
Classifier: Topic :: Software Development :: Libraries :: Python Modules
Requires-Python: <3.14,>=3.12
Requires-Dist: aiohttp>=3.10
Requires-Dist: beautifulsoup4>=4.12
Requires-Dist: lxml>=5.3
Requires-Dist: orjson>=3.10
Provides-Extra: qrcode
Requires-Dist: pillow>=11.0; extra == 'qrcode'
Requires-Dist: pymupdf>=1.25; extra == 'qrcode'
